<texts>	<info>			LAVAPOOLS							</info>		
<info>	DIALOG_ID			ENGLISH			FRENCH			EN_COUNT	FR_COUNT	</info>	
<entry id='	4EDGESGAMES	'>	<english>	4EdgesGames	</english>	<french>	4EdgesGames	</french>	<info>	11	11	</info>	</entry>
<entry id='	BEST_CONT	'>	<english>	0	</english>	<french>	0	</french>	<info>	1	1	</info>	</entry>
<entry id='	BEST_LABEL	'>	<english>	BEST	</english>	<french>	RECORD	</french>	<info>	4	6	</info>	</entry>
<entry id='	CREDITS_BTN	'>	<english>	Credits	</english>	<french>	Crédits	</french>	<info>	7	7	</info>	</entry>
<entry id='	CREDITS_LABEL	'>	<english>	Credits	</english>	<french>	Crédits	</french>	<info>	7	7	</info>	</entry>
<entry id='	EXIT_BTN	'>	<english>	Exit	</english>	<french>	Quitter	</french>	<info>	4	7	</info>	</entry>
<entry id='	GAME_VERSION	'>	<english>	Paid version/nAlpha_v2	</english>	<french>	Version Payante/nAlpha_v2	</french>	<info>	22	25	</info>	</entry>
<entry id='	JULIEN	'>	<english>	Julien Commerenc	</english>	<french>	Julien Commerenc	</french>	<info>	16	16	</info>	</entry>
<entry id='	JULIEN_LABEL	'>	<english>	Music	</english>	<french>	Musique	</french>	<info>	5	7	</info>	</entry>
<entry id='	LB_HEADER	'>	<english>	Leaderboard	</english>	<french>	Tableau scores	</french>	<info>	11	14	</info>	</entry>
<entry id='	LEVEL_NAME	'>	<english>	Level Name	</english>	<french>	Nom du niveau	</french>	<info>	10	13	</info>	</entry>
<entry id='	LUDOVIC	'>	<english>	Ludovic Servat	</english>	<french>	Ludovic Servat	</french>	<info>	14	14	</info>	</entry>
<entry id='	LUDOVIC_LABEL	'>	<english>	Game design - GFX	</english>	<french>	Game design - GFX	</french>	<info>	17	17	</info>	</entry>
<entry id='	LVL_LABEL	'>	<english>	Rank	</english>	<french>	Rang	</french>	<info>	4	4	</info>	</entry>
<entry id='	MUTE_GLOBAL_BTN	'>	<english>	Muted	</english>	<french>	Muet	</french>	<info>	5	4	</info>	</entry>
<entry id='	MUTE_GLOBAL_LABEL	'>	<english>	All sounds	</english>	<french>	Tout les sons	</french>	<info>	10	13	</info>	</entry>
<entry id='	MUTE_MUSIC_BTN	'>	<english>	Muted	</english>	<french>	Muet	</french>	<info>	5	4	</info>	</entry>
<entry id='	MUTE_MUSIC_LABEL	'>	<english>	Music	</english>	<french>	Musique	</french>	<info>	5	7	</info>	</entry>
<entry id='	OBJECTIVE	'>	<english>	Gather 25 gate parts to open the door	</english>	<french>	Ramasse 25 morceaux de portes pour ouvrir la porte	</french>	<info>	37	50	</info>	</entry>
<entry id='	OPTIONS_BTN	'>	<english>	Options	</english>	<french>	Options	</french>	<info>	7	7	</info>	</entry>
<entry id='	PAUL	'>	<english>	Paul Lagarrigue	</english>	<french>	Paul Lagarrigue	</french>	<info>	15	15	</info>	</entry>
<entry id='	PAUL_LABEL	'>	<english>	Sound design - Music	</english>	<french>	Sound design - Music	</french>	<info>	20	20	</info>	</entry>
<entry id='	PLAY_NEXT	'>	<english>	Press Enter to play Next Level	</english>	<french>	Appuyez sur Entrée pour jouer au prochain niveau	</french>	<info>	30	48	</info>	</entry>
<entry id='	PLAYER_NOTIF	'>	<english>	Where am I ?	</english>	<french>	Où suis-je ?	</french>	<info>	12	12	</info>	</entry>
<entry id='	RESPAWN_CMD	'>	<english>	Press Enter to play again	</english>	<french>	Appuyez sur Entrée pour rejouer	</french>	<info>	25	31	</info>	</entry>
<entry id='	RESPAWN_HEAD	'>	<english>	Krabby died miserably	</english>	<french>	Krabby est mort misérablement	</french>	<info>	21	29	</info>	</entry>
<entry id='	SCORE_CONT	'>	<english>	0	</english>	<french>	0	</french>	<info>	1	1	</info>	</entry>
<entry id='	SCORE_LAB	'>	<english>	SCORE	</english>	<french>	SCORE	</french>	<info>	5	5	</info>	</entry>
<entry id='	START_BTN	'>	<english>	Play	</english>	<french>	Jouer	</french>	<info>	4	5	</info>	</entry>
<entry id='	START_CMD	'>	<english>	Press Enter to play	</english>	<french>	Appuyez sur Entrée pour jouer	</french>	<info>	19	29	</info>	</entry>
<entry id='	YANNICK	'>	<english>	Yannick Elahee	</english>	<french>	Yannick Elahee	</french>	<info>	14	14	</info>	</entry>
<entry id='	YANNICK_LABEL	'>	<english>	Game design - Code	</english>	<french>	Game design - Code	</french>	<info>	18	18	</info>	</entry>
<entry id='	SUCCEED	'>	<english>	You escaped from	</english>	<french>	Vous vous êtes enfui de	</french>	<info>	16	23	</info>	</entry>
<entry id='	PLAY_LABEL	'>	<english>	Play	</english>	<french>	Jouer	</french>	<info>	4	5	</info>	</entry>
<entry id='	GAME_WIP	'>	<english>	You reached the end of the Alpha !/n Please stay in touch to get further updates.	</english>	<french>	Vous avez atteint la fin de l'Alpha !/nRestez au courant pour jouer aux prochains niveaux	</french>	<info>	81	89	</info>	</entry>
<entry id='		'>	<english>		</english>	<french>		</french>	<info>	0	0	</info>	</entry>
<entry id='		'>	<english>		</english>	<french>		</french>	<info>	0	0	</info>	</entry>
<entry id='		'>	<english>		</english>	<french>		</french>	<info>	0	0	</info>	</entry>
<entry id='		'>	<english>		</english>	<french>		</french>	<info>	0	0	</info>	</entry>
<entry id='		'>	<english>		</english>	<french>		</french>	<info>	0	0	</info>	</entry>
<entry id='		'>	<english>		</english>	<french>		</french>	<info>	0	0	</info>	</entry>
<entry id='		'>	<english>		</english>	<french>		</french>	<info>	0	0	</info>	</entry>
<entry id='		'>	<english>		</english>	<french>		</french>	<info>	0	0	</info>	</entry>
<entry id='		'>	<english>		</english>	<french>		</french>	<info>	0	0	</info>	</entry>
<entry id='		'>	<english>		</english>	<french>		</french>	<info>	0	0	</info>	</entry>
<entry id='		'>	<english>		</english>	<french>		</french>	<info>	0	0	</info>	</entry>
<entry id='		'>	<english>		</english>	<french>		</french>	<info>	0	0	</info>	</entry>
<entry id='		'>	<english>		</english>	<french>		</french>	<info>	0	0	</info>	</entry>
<entry id='		'>	<english>		</english>	<french>		</french>	<info>	0	0	</info>	</entry>
<entry id='		'>	<english>		</english>	<french>		</french>	<info>	0	0	</info>	</entry>
<entry id='		'>	<english>		</english>	<french>		</french>	<info>	0	0	</info>	</entry>
<entry id='		'>	<english>		</english>	<french>		</french>	<info>	0	0	</info>	</entry>
<entry id='		'>	<english>		</english>	<french>		</french>	<info>	0	0	</info>	</entry>
<entry id='		'>	<english>		</english>	<french>		</french>	<info>	0	0	</info>	</entry>
<entry id='		'>	<english>		</english>	<french>		</french>	<info>	0	0	</info>	</entry>
<entry id='		'>	<english>		</english>	<french>		</french>	<info>	0	0	</info>	</entry>
<entry id='		'>	<english>		</english>	<french>		</french>	<info>	0	0	</info>	</entry>
<entry id='		'>	<english>		</english>	<french>		</french>	<info>	0	0	</info>	</entry>
<entry id='		'>	<english>		</english>	<french>		</french>	<info>	0	0	</info>	</entry>
<entry id='		'>	<english>		</english>	<french>		</french>	<info>	0	0	</info>	</entry>
<entry id='		'>	<english>		</english>	<french>		</french>	<info>	0	0	</info>	</entry>
<entry id='		'>	<english>		</english>	<french>		</french>	<info>	0	0	</info>	</entry>
<entry id='		'>	<english>		</english>	<french>		</french>	<info>	0	0	</info>	</entry>
<entry id='		'>	<english>		</english>	<french>		</french>	<info>	0	0	</info>	</entry>
<entry id='		'>	<english>		</english>	<french>		</french>	<info>	0	0	</info>	</entry>
<entry id='		'>	<english>		</english>	<french>		</french>	<info>	0	0	</info>	</entry>
<entry id='		'>	<english>		</english>	<french>		</french>	<info>	0	0	</info>	</entry>
<entry id='		'>	<english>		</english>	<french>		</french>	<info>	0	0	</info>	</entry>
<entry id='		'>	<english>		</english>	<french>		</french>	<info>	0	0	</info>	</entry>
<entry id='		'>	<english>		</english>	<french>		</french>	<info>	0	0	</info>	</entry>
<entry id='		'>	<english>		</english>	<french>		</french>	<info>	0	0	</info>	</entry>
<entry id='		'>	<english>		</english>	<french>		</french>	<info>	0	0	</info>	</entry>
<entry id='		'>	<english>		</english>	<french>		</french>	<info>	0	0	</info>	</entry>
<entry id='		'>	<english>		</english>	<french>		</french>	<info>	0	0	</info>	</entry>
<entry id='		'>	<english>		</english>	<french>		</french>	<info>	0	0	</info>	</entry>
<entry id='		'>	<english>		</english>	<french>		</french>	<info>	0	0	</info>	</entry>
<entry id='		'>	<english>		</english>	<french>		</french>	<info>	0	0	</info>	</entry>
<entry id='		'>	<english>		</english>	<french>		</french>	<info>	0	0	</info>	</entry>
<entry id='		'>	<english>		</english>	<french>		</french>	<info>	0	0	</info>	</entry>
<entry id='		'>	<english>		</english>	<french>		</french>	<info>	0	0	</info>	</entry>
<entry id='		'>	<english>		</english>	<french>		</french>	<info>	0	0	</info>	</entry>
<entry id='		'>	<english>		</english>	<french>		</french>	<info>	0	0	</info>	</entry>
<entry id='		'>	<english>		</english>	<french>		</french>	<info>	0	0	</info>	</entry>
<entry id='		'>	<english>		</english>	<french>		</french>	<info>	0	0	</info>	</entry>
<entry id='		'>	<english>		</english>	<french>		</french>	<info>	0	0	</info>	</entry>
<entry id='		'>	<english>		</english>	<french>		</french>	<info>	0	0	</info>	</entry>
<entry id='		'>	<english>		</english>	<french>		</french>	<info>	0	0	</info>	</entry>
<entry id='		'>	<english>		</english>	<french>		</french>	<info>	0	0	</info>	</entry>
<entry id='		'>	<english>		</english>	<french>		</french>	<info>	0	0	</info>	</entry>
<entry id='		'>	<english>		</english>	<french>		</french>	<info>	0	0	</info>	</entry>
<entry id='		'>	<english>		</english>	<french>		</french>	<info>	0	0	</info>	</entry>
<entry id='		'>	<english>		</english>	<french>		</french>	<info>	0	0	</info>	</entry>
<entry id='		'>	<english>		</english>	<french>		</french>	<info>	0	0	</info>	</entry>
<entry id='		'>	<english>		</english>	<french>		</french>	<info>	0	0	</info>	</entry>
<entry id='		'>	<english>		</english>	<french>		</french>	<info>	0	0	</info>	</entry>
<entry id='		'>	<english>		</english>	<french>		</french>	<info>	0	0	</info>	</entry>
<entry id='		'>	<english>		</english>	<french>		</french>	<info>	0	0	</info>	</entry>
<entry id='		'>	<english>		</english>	<french>		</french>	<info>	0	0	</info>	</entry>
<entry id='		'>	<english>		</english>	<french>		</french>	<info>	0	0	</info>	</entry>
<entry id='		'>	<english>		</english>	<french>		</french>	<info>	0	0	</info>	</entry>
<entry id='		'>	<english>		</english>	<french>		</french>	<info>	0	0	</info>	</entry>
<entry id='		'>	<english>		</english>	<french>		</french>	<info>	0	0	</info>	</entry>
<entry id='		'>	<english>		</english>	<french>		</french>	<info>	0	0	</info>	</entry>
<entry id='		'>	<english>		</english>	<french>		</french>	<info>	0	0	</info>	</entry>
<entry id='		'>	<english>		</english>	<french>		</french>	<info>	0	0	</info>	</entry>
<entry id='		'>	<english>		</english>	<french>		</french>	<info>	0	0	</info>	</entry>
<entry id='		'>	<english>		</english>	<french>		</french>	<info>	0	0	</info>	</entry>
<entry id='		'>	<english>		</english>	<french>		</french>	<info>	0	0	</info>	</entry>
<entry id='		'>	<english>		</english>	<french>		</french>	<info>	0	0	</info>	</entry>
<entry id='		'>	<english>		</english>	<french>		</french>	<info>	0	0	</info>	</entry>
<entry id='		'>	<english>		</english>	<french>		</french>	<info>	0	0	</info>	</entry>
<entry id='		'>	<english>		</english>	<french>		</french>	<info>	0	0	</info>	</entry>
</texts>													